mne_icalabel/__init__.py
mne_icalabel/__init__.pyi
mne_icalabel/_version.py
mne_icalabel/config.py
mne_icalabel/config.pyi
mne_icalabel/conftest.py
mne_icalabel/label_components.py
mne_icalabel/label_components.pyi
mne_icalabel/annotation/__init__.py
mne_icalabel/annotation/__init__.pyi
mne_icalabel/annotation/bids.py
mne_icalabel/annotation/bids.pyi
mne_icalabel/commands/__init__.py
mne_icalabel/commands/mne_gui_ic_annotation.py
mne_icalabel/commands/sys_info.py
mne_icalabel/datasets/__init__.py
mne_icalabel/datasets/__init__.pyi
mne_icalabel/datasets/icalabel/__init__.py
mne_icalabel/datasets/icalabel/__init__.pyi
mne_icalabel/datasets/icalabel/icalabel.py
mne_icalabel/datasets/icalabel/icalabel.pyi
mne_icalabel/features/__init__.py
mne_icalabel/features/__init__.pyi
mne_icalabel/features/topomap.py
mne_icalabel/features/topomap.pyi
mne_icalabel/gui/__init__.py
mne_icalabel/gui/__init__.pyi
mne_icalabel/gui/_label_components.py
mne_icalabel/gui/_label_components.pyi
mne_icalabel/iclabel/__init__.py
mne_icalabel/iclabel/__init__.pyi
mne_icalabel/iclabel/_config.py
mne_icalabel/iclabel/_config.pyi
mne_icalabel/iclabel/_utils.py
mne_icalabel/iclabel/_utils.pyi
mne_icalabel/iclabel/features.py
mne_icalabel/iclabel/features.pyi
mne_icalabel/iclabel/label_components.py
mne_icalabel/iclabel/label_components.pyi
mne_icalabel/iclabel/network/__init__.py
mne_icalabel/iclabel/network/__init__.pyi
mne_icalabel/iclabel/network/onnx.py
mne_icalabel/iclabel/network/onnx.pyi
mne_icalabel/iclabel/network/torch.py
mne_icalabel/iclabel/network/torch.pyi
mne_icalabel/iclabel/network/utils.py
mne_icalabel/iclabel/network/utils.pyi
mne_icalabel/iclabel/network/assets/ICLabelNet.onnx
mne_icalabel/iclabel/network/assets/ICLabelNet.pt
mne_icalabel/megnet/__init__.py
mne_icalabel/megnet/__init__.pyi
mne_icalabel/megnet/_config.py
mne_icalabel/megnet/_config.pyi
mne_icalabel/megnet/_utils.py
mne_icalabel/megnet/_utils.pyi
mne_icalabel/megnet/features.py
mne_icalabel/megnet/features.pyi
mne_icalabel-0.8.1.dist-info/licenses/LICENSE
mne_icalabel-0.8.1.dist-info/METADATA
mne_icalabel-0.8.1.dist-info/WHEEL
mne_icalabel-0.8.1.dist-info/entry_points.txt
mne_icalabel-0.8.1.dist-info/top_level.txt
mne_icalabel-0.8.1.dist-info/RECORD
