Metadata-Version: 2.4
Name: mne-icalabel
Version: 0.8.1
Summary: MNE-ICALabel: Automatic labeling of ICA components from MEG, EEG and iEEG data with MNE.
Maintainer-email: Adam Li <adam.li@columbia.edu>, Mathieu Scheltienne <mathieu.scheltienne@gnail.com>
License: BSD 3-Clause License
Project-URL: documentation, https://mne.tools/mne-icalabel
Project-URL: source, https://github.com/mne-tools/mne-icalabel
Project-URL: tracker, https://github.com/mne-tools/mne-icalabel/issues
Keywords: eeg,ica,ieeg,meg,neuroscience
Classifier: Intended Audience :: Developers
Classifier: Intended Audience :: Science/Research
Classifier: License :: OSI Approved :: BSD License
Classifier: Natural Language :: English
Classifier: Operating System :: MacOS
Classifier: Operating System :: Microsoft :: Windows
Classifier: Operating System :: Unix
Classifier: Programming Language :: Python :: 3 :: Only
Classifier: Programming Language :: Python :: 3.10
Classifier: Programming Language :: Python :: 3.11
Classifier: Programming Language :: Python :: 3.12
Classifier: Programming Language :: Python :: 3.13
Classifier: Programming Language :: Python :: 3.14
Classifier: Topic :: Scientific/Engineering
Classifier: Topic :: Software Development
Requires-Python: >=3.10
License-File: LICENSE
Requires-Dist: mne>=1.2
Requires-Dist: numpy>=1.21
Requires-Dist: packaging
Requires-Dist: pooch
Requires-Dist: psutil
Requires-Dist: scipy>=1.4.0
Provides-Extra: all
Requires-Dist: mne-icalabel[build]; extra == "all"
Requires-Dist: mne-icalabel[doc]; extra == "all"
Requires-Dist: mne-icalabel[gui]; extra == "all"
Requires-Dist: mne-icalabel[ica]; extra == "all"
Requires-Dist: mne-icalabel[onnx]; extra == "all"
Requires-Dist: mne-icalabel[stubs]; extra == "all"
Requires-Dist: mne-icalabel[style]; extra == "all"
Requires-Dist: mne-icalabel[test]; extra == "all"
Requires-Dist: mne-icalabel[torch]; extra == "all"
Provides-Extra: build
Requires-Dist: build; extra == "build"
Requires-Dist: twine; extra == "build"
Provides-Extra: doc
Requires-Dist: memory-profiler; extra == "doc"
Requires-Dist: mne-icalabel[gui]; extra == "doc"
Requires-Dist: mne-icalabel[ica]; extra == "doc"
Requires-Dist: mne-icalabel[onnx]; extra == "doc"
Requires-Dist: numpydoc; extra == "doc"
Requires-Dist: pydata-sphinx-theme==0.14.1; extra == "doc"
Requires-Dist: PyQt6; extra == "doc"
Requires-Dist: sphinx; extra == "doc"
Requires-Dist: sphinx-copybutton; extra == "doc"
Requires-Dist: sphinx-design; extra == "doc"
Requires-Dist: sphinx-gallery; extra == "doc"
Requires-Dist: sphinx-issues; extra == "doc"
Requires-Dist: sphinxcontrib-bibtex; extra == "doc"
Provides-Extra: full
Requires-Dist: mne-icalabel[all]; extra == "full"
Provides-Extra: gui
Requires-Dist: matplotlib; extra == "gui"
Requires-Dist: mne-qt-browser>=0.6.0; extra == "gui"
Requires-Dist: qtpy; extra == "gui"
Provides-Extra: ica
Requires-Dist: joblib; extra == "ica"
Requires-Dist: python-picard; extra == "ica"
Requires-Dist: scikit-learn; extra == "ica"
Provides-Extra: onnx
Requires-Dist: onnxruntime; extra == "onnx"
Provides-Extra: stubs
Requires-Dist: isort; extra == "stubs"
Requires-Dist: mne-icalabel[gui]; extra == "stubs"
Requires-Dist: mne-icalabel[onnx]; extra == "stubs"
Requires-Dist: mne-icalabel[torch]; extra == "stubs"
Requires-Dist: mypy; extra == "stubs"
Requires-Dist: PyQt6; extra == "stubs"
Requires-Dist: ruff>=0.6.0; extra == "stubs"
Provides-Extra: style
Requires-Dist: bibclean; extra == "style"
Requires-Dist: codespell[toml]>=2.2.4; extra == "style"
Requires-Dist: ruff>=0.6.0; extra == "style"
Requires-Dist: toml-sort; extra == "style"
Requires-Dist: yamllint; extra == "style"
Provides-Extra: test
Requires-Dist: mne-bids>=0.14; extra == "test"
Requires-Dist: mne-icalabel[gui]; extra == "test"
Requires-Dist: mne-icalabel[ica]; extra == "test"
Requires-Dist: pandas; extra == "test"
Requires-Dist: pymatreader; extra == "test"
Requires-Dist: PyQt6; extra == "test"
Requires-Dist: pytest-cov; extra == "test"
Requires-Dist: pytest>=8.0.0; extra == "test"
Provides-Extra: torch
Requires-Dist: torch; extra == "torch"
Dynamic: license-file
